tagging_system/__init__.py
tagging_system/aggregator/SimpleAggr.py
tagging_system/aggregator/__init__.py
tagging_system/handler/DiscordHandler.py
tagging_system/handler/GenericHandler.py
tagging_system/handler/TwitterHandler.py
tagging_system/handler/__init__.py
tagging_system/main.py
tagging_system/preprocessor/DiscordPreprocessor.py
tagging_system/preprocessor/GenericPreprocessor.py
tagging_system/preprocessor/TextProcessing.py
tagging_system/preprocessor/TextProcessingLiterals.py
tagging_system/preprocessor/TwitterPreprocessor.py
tagging_system/preprocessor/__init__.py
tagging_system/strategy/DiscordChannelMapping.py
tagging_system/strategy/DiscordServerMapping.py
tagging_system/strategy/DiscordSimpleRegex.py
tagging_system/strategy/DiscordUserMapping.py
tagging_system/strategy/GenericSimpleRegex.py
tagging_system/strategy/TwitterSimpleEntity.py
tagging_system/strategy/TwitterSimpleRegex.py
tagging_system/strategy/TwitterSimpleUserMapping.py
tagging_system/strategy/__init__.py
tagging_system-0.1.0.dist-info/WHEEL
tagging_system-0.1.0.dist-info/METADATA
tagging_system-0.1.0.dist-info/RECORD
